mujoco_mocapper/__init__.py
mujoco_mocapper/mocap_move.py
mujoco_mocapper/mujoco_mocapper.py
mujoco_mocapper/xml_view.py
mujoco_mocapper-0.0.1.data/scripts/mujoco-mocapper
mujoco_mocapper-0.0.1.data/scripts/mujoco-mocapper.py
mujoco_mocapper-0.0.1.dist-info/METADATA
mujoco_mocapper-0.0.1.dist-info/WHEEL
mujoco_mocapper-0.0.1.dist-info/top_level.txt
mujoco_mocapper-0.0.1.dist-info/RECORD
